{
  "date": "2026-06-20",
  "chapters": [
    {
      "title": "The Trillion Dollar Gap | Aswath Damodaran on SpaceX, AI and the Big Market Delusion",
      "start_s": 44.234286
    },
    {
      "title": "Bryan Taylor: The Four Forces That Drive Every Market (Investing in America Series) #635",
      "start_s": 216.80163299999998
    },
    {
      "title": "Bryan Taylor: The Four Forces That Drive Every Market (Investing in America Series) #635",
      "start_s": 384.721905
    },
    {
      "title": "How Substack Creators Are Covering This Strange Markets Era",
      "start_s": 542.335692
    },
    {
      "title": "How Substack Creators Are Covering This Strange Markets Era",
      "start_s": 709.7606359999999
    }
  ],
  "sources": [
    {
      "title": "The Trillion Dollar Gap | Aswath Damodaran on SpaceX, AI and the Big Market Delusion",
      "podcast": "Excess Returns",
      "link": "https://podcasters.spotify.com/pod/show/excess-returns/episodes/The-Trillion-Dollar-Gap--Aswath-Damodaran-on-SpaceX--AI-and-the-Big-Market-Delusion-e3l007v",
      "audio_url": "https://traffic.megaphone.fm/APO2274232333.mp3",
      "transcript_url": "",
      "published": "2026-06-19T01:00:00+00:00"
    },
    {
      "title": "Bryan Taylor: The Four Forces That Drive Every Market (Investing in America Series) #635",
      "podcast": "The Meb Faber Show - Better Investing",
      "link": "",
      "audio_url": "https://traffic.megaphone.fm/TIFM2175184998.mp3",
      "transcript_url": "",
      "published": "2026-06-19T08:30:00+00:00"
    },
    {
      "title": "How Substack Creators Are Covering This Strange Markets Era",
      "podcast": "Odd Lots",
      "link": "https://omny.fm/shows/odd-lots/how-substack-creators-are-covering-this-strange-markets-era",
      "audio_url": "https://podtrac.com/pts/redirect.mp3/tracking.swap.fm/track/UVBrz8bN8aM2Xe47PEPu/traffic.omny.fm/d/clips/e73c998e-6e60-432f-8610-ae210140c5b1/8a94442e-5a74-4fa2-8b8d-ae27003a8d6b/af2e1113-d234-4b94-89ce-b46d0139fa3f/audio.mp3?utm_source=Podcast&in_playlist=982f5071-765c-403d-969d-ae27003a8d83",
      "transcript_url": "",
      "published": "2026-06-20T08:00:00+00:00"
    }
  ],
  "transcript_file": "transcript_2026-06-20.txt"
}